{
  "_class": "text",
  "attributedString": {
    "_class": "attributedString",
    "attributes": [
      {
        "_class": "stringAttribute",
        "attributes": {
          "MSAttributedStringColorAttribute": {
            "_class": "color",
            "alpha": 1,
            "blue": 0,
            "green": 0.3137254901960784,
            "red": 1
          },
          "MSAttributedStringFontAttribute": {
            "_class": "fontDescriptor",
            "attributes": {
              "name": "OpenSans",
              "size": 14
            }
          },
          "kerning": 0,
          "paragraphStyle": {
            "_class": "paragraphStyle",
            "alignment": 0,
            "allowsDefaultTighteningForTruncation": 0,
            "maximumLineHeight": 18,
            "minimumLineHeight": 18
          },
          "textStyleVerticalAlignmentKey": 0
        },
        "length": 4,
        "location": 0
      }
    ],
    "string": "Body"
  },
  "automaticallyDrawOnUnderlyingPath": false,
  "do_objectID": "12C5B8E3-4B2B-4ED2-A00C-E746B6EF2BDD",
  "dontSynchroniseWithSymbol": false,
  "exportOptions": {
    "_class": "exportOptions",
    "do_objectID": "5C093253-8F93-4D1F-B731-DB3E4F3308C3",
    "exportFormats": [
    ],
    "includedLayerIds": [
    ],
    "layerOptions": 0,
    "shouldTrim": false
  },
  "frame": {
    "_class": "rect",
    "constrainProportions": false,
    "do_objectID": "7CB6A606-59C9-4071-89D0-D065260F9C62",
    "height": 24,
    "width": 221,
    "x": 427,
    "y": 966
  },
  "glyphBounds": "{{1, 3}, {33, 15}}",
  "isFlippedHorizontal": false,
  "isFlippedVertical": false,
  "isLocked": false,
  "isVisible": true,
  "layerListExpandedType": 0,
  "lineSpacingBehaviour": 2,
  "name": "Body/Primary #2/Regular",
  "nameIsFixed": false,
  "resizingConstraint": 63,
  "resizingType": 0,
  "rotation": 0,
  "shouldBreakMaskChain": false,
  "style": {
    "_class": "style",
    "do_objectID": "BD0A2AA0-9F2F-4A4E-A587-32B74508380A",
    "endDecorationType": 0,
    "miterLimit": 10,
    "sharedObjectID": "C18EAA17-0A6C-4CF7-B2B8-16208C5CD33D",
    "startDecorationType": 0,
    "textStyle": {
      "_class": "textStyle",
      "do_objectID": "0B3A71A9-5BD1-402F-9E09-FD5F2D0B8A41",
      "encodedAttributes": {
        "MSAttributedStringColorAttribute": {
          "_class": "color",
          "alpha": 1,
          "blue": 0,
          "green": 0.3137254901960784,
          "red": 1
        },
        "MSAttributedStringFontAttribute": {
          "_class": "fontDescriptor",
          "attributes": {
            "name": "OpenSans",
            "size": 14
          }
        },
        "kerning": 0,
        "paragraphStyle": {
          "_class": "paragraphStyle",
          "alignment": 0,
          "allowsDefaultTighteningForTruncation": 0,
          "maximumLineHeight": 18,
          "minimumLineHeight": 18
        },
        "textStyleVerticalAlignmentKey": 0
      },
      "verticalAlignment": 0
    }
  },
  "textBehaviour": 2
}